{
	"@type":"Subset",
	"Name":"Contas Nível Top",
	"Alias":"Descrição",
	"Elements":
	[
		{
			"@id":"Dimensions('ALL.D.CONTAS_BALANCETE')/Hierarchies('ALL.D.CONTAS_BALANCETE')/Elements('1')"
		},
		{
			"@id":"Dimensions('ALL.D.CONTAS_BALANCETE')/Hierarchies('ALL.D.CONTAS_BALANCETE')/Elements('2')"
		},
		{
			"@id":"Dimensions('ALL.D.CONTAS_BALANCETE')/Hierarchies('ALL.D.CONTAS_BALANCETE')/Elements('3')"
		},
		{
			"@id":"Dimensions('ALL.D.CONTAS_BALANCETE')/Hierarchies('ALL.D.CONTAS_BALANCETE')/Elements('4')"
		},
		{
			"@id":"Dimensions('ALL.D.CONTAS_BALANCETE')/Hierarchies('ALL.D.CONTAS_BALANCETE')/Elements('5')"
		}
	]
}